[
  {
    "id": "cmn9fbqul061se90wu74emssr",
    "sku": "bc634-las-00",
    "oldTags": [
      "Brabus",
      "Tuning",
      "Bentley",
      "Bentley Continental GT Speed"
    ],
    "newTags": [
      "Brabus",
      "Tuning",
      "Bentley",
      "Bentley Continental GTC Speed"
    ]
  },
  {
    "id": "cmn9fbqu9061ge90w1e8x3eun",
    "sku": "bc634-008-00",
    "oldTags": [
      "Brabus",
      "Tuning",
      "Bentley",
      "Bentley Continental GT Speed"
    ],
    "newTags": [
      "Brabus",
      "Tuning",
      "Bentley",
      "Bentley Continental GTC Speed"
    ]
  },
  {
    "id": "cmmuk5gap018ye9v8o0x6paq8",
    "sku": "URB-EXH-25358155-V1",
    "oldTags": [
      "Car-Part",
      "Origin-GB",
      "Status-Active",
      "urban-family:bodykits",
      "Bentley",
      "Continental GT",
      "Exhaust",
      "Urban Automotive",
      "store:urban",
      "urban-source:gp-portal",
      "urban-vehicle-brand:bentley",
      "urban-manufacturer:urban-automotive"
    ],
    "newTags": [
      "Car-Part",
      "Origin-GB",
      "Status-Active",
      "urban-family:bodykits",
      "Bentley",
      "Continental GT",
      "Exhaust",
      "Urban Automotive",
      "store:urban",
      "urban-source:gp-portal",
      "urban-vehicle-brand:bentley",
      "urban-manufacturer:urban-automotive",
      "Bentley Continental GT Speed"
    ]
  },
  {
    "id": "cmn9fbqtj060se90woz1soyo1",
    "sku": "bc634-463-99",
    "oldTags": [
      "Brabus",
      "Tuning",
      "Bentley",
      "Bentley Continental GT Speed"
    ],
    "newTags": [
      "Brabus",
      "Tuning",
      "Bentley",
      "Bentley Continental GTC Speed"
    ]
  },
  {
    "id": "cmmuk5fia00kre9v81a5s3337",
    "sku": "URB-GRI-25358151-V1",
    "oldTags": [
      "Car-Part",
      "Origin-GB",
      "Status-Active",
      "urban-family:exterior",
      "Bentley",
      "Continental GT",
      "Grilles",
      "Urban Automotive",
      "store:urban",
      "urban-source:gp-portal",
      "urban-vehicle-brand:bentley",
      "urban-manufacturer:urban-automotive"
    ],
    "newTags": [
      "Car-Part",
      "Origin-GB",
      "Status-Active",
      "urban-family:exterior",
      "Bentley",
      "Continental GT",
      "Grilles",
      "Urban Automotive",
      "store:urban",
      "urban-source:gp-portal",
      "urban-vehicle-brand:bentley",
      "urban-manufacturer:urban-automotive",
      "Bentley Continental GT Speed"
    ]
  },
  {
    "id": "cmn9fbqvz0640e90wz3x5lr67",
    "sku": "bc634-851-01",
    "oldTags": [
      "Brabus",
      "Tuning",
      "Bentley",
      "Bentley Continental GT Speed"
    ],
    "newTags": [
      "Brabus",
      "Tuning",
      "Bentley",
      "Bentley Continental GTC Speed"
    ]
  },
  {
    "id": "cmn9fbqtw0617e90wvbj6k0vw",
    "sku": "bc634-670-08",
    "oldTags": [
      "Brabus",
      "Tuning",
      "Bentley",
      "Bentley Continental GT Speed"
    ],
    "newTags": [
      "Brabus",
      "Tuning",
      "Bentley",
      "Bentley Continental GTC Speed"
    ]
  },
  {
    "id": "cmmuk5gki01iue9v8hzi6xt1d",
    "sku": "URB-FRO-25358152-V1",
    "oldTags": [
      "Car-Part",
      "Origin-GB",
      "Status-Active",
      "urban-family:exterior",
      "Bentley",
      "Continental GT",
      "Front Bumper Add-ons",
      "Urban Automotive",
      "store:urban",
      "urban-source:gp-portal",
      "urban-vehicle-brand:bentley",
      "urban-manufacturer:urban-automotive"
    ],
    "newTags": [
      "Car-Part",
      "Origin-GB",
      "Status-Active",
      "urban-family:exterior",
      "Bentley",
      "Continental GT",
      "Front Bumper Add-ons",
      "Urban Automotive",
      "store:urban",
      "urban-source:gp-portal",
      "urban-vehicle-brand:bentley",
      "urban-manufacturer:urban-automotive",
      "Bentley Continental GT Speed"
    ]
  },
  {
    "id": "cmn9fbqtc060ke90wja2sxzdk",
    "sku": "bc634-263-99",
    "oldTags": [
      "Brabus",
      "Tuning",
      "Bentley",
      "Bentley Continental GT Speed"
    ],
    "newTags": [
      "Brabus",
      "Tuning",
      "Bentley",
      "Bentley Continental GTC Speed"
    ]
  },
  {
    "id": "cmn9fbqux062ce90wrjcis81h",
    "sku": "bc634-350-00",
    "oldTags": [
      "Brabus",
      "Tuning",
      "Bentley",
      "Bentley Continental GT Speed"
    ],
    "newTags": [
      "Brabus",
      "Tuning",
      "Bentley",
      "Bentley Continental GTC Speed"
    ]
  },
  {
    "id": "cmn9fbqur0622e90wmfnpnth0",
    "sku": "bc634-816-00",
    "oldTags": [
      "Brabus",
      "Tuning",
      "Bentley",
      "Bentley Continental GT Speed"
    ],
    "newTags": [
      "Brabus",
      "Tuning",
      "Bentley",
      "Bentley Continental GTC Speed"
    ]
  },
  {
    "id": "cmn9fbqv3062me90wap28e9rr",
    "sku": "bc634-816-20",
    "oldTags": [
      "Brabus",
      "Tuning",
      "Bentley",
      "Bentley Continental GT Speed"
    ],
    "newTags": [
      "Brabus",
      "Tuning",
      "Bentley",
      "Bentley Continental GTC Speed"
    ]
  },
  {
    "id": "cmn9fbqvt063qe90wpcekbdeg",
    "sku": "bc634-851-00",
    "oldTags": [
      "Brabus",
      "Tuning",
      "Bentley",
      "Bentley Continental GT Speed"
    ],
    "newTags": [
      "Brabus",
      "Tuning",
      "Bentley",
      "Bentley Continental GTC Speed"
    ]
  },
  {
    "id": "cmn9fbqv9062we90wuj0d94qv",
    "sku": "bc634-890-carbon",
    "oldTags": [
      "Brabus",
      "Tuning",
      "Bentley",
      "Bentley Continental GT Speed"
    ],
    "newTags": [
      "Brabus",
      "Tuning",
      "Bentley",
      "Bentley Continental GTC Speed"
    ]
  },
  {
    "id": "cmn9fbquf061me90wg2e1mis2",
    "sku": "zm12-bc-pe",
    "oldTags": [
      "Brabus",
      "Tuning",
      "Bentley",
      "Bentley Continental GT Speed"
    ],
    "newTags": [
      "Brabus",
      "Tuning",
      "Bentley",
      "Bentley Continental GTC Speed"
    ]
  },
  {
    "id": "cmmuk5ht602nie9v86130qwjo",
    "sku": "URB-TAI-25358154-V1",
    "oldTags": [
      "Car-Part",
      "Origin-GB",
      "Status-Active",
      "urban-family:wheels",
      "Bentley",
      "Continental GT",
      "Tailpipes",
      "Urban Automotive",
      "store:urban",
      "urban-source:gp-portal",
      "urban-vehicle-brand:bentley",
      "urban-manufacturer:urban-automotive"
    ],
    "newTags": [
      "Car-Part",
      "Origin-GB",
      "Status-Active",
      "urban-family:wheels",
      "Bentley",
      "Continental GT",
      "Tailpipes",
      "Urban Automotive",
      "store:urban",
      "urban-source:gp-portal",
      "urban-vehicle-brand:bentley",
      "urban-manufacturer:urban-automotive",
      "Bentley Continental GT Speed"
    ]
  },
  {
    "id": "cmmuk5f7200bce9v89k3r7v7v",
    "sku": "URB-ARC-25358153-V1",
    "oldTags": [
      "Car-Part",
      "Origin-GB",
      "Status-Active",
      "urban-family:exterior",
      "Arches",
      "Bentley",
      "Continental GT",
      "Urban Automotive",
      "store:urban",
      "urban-source:gp-portal",
      "urban-vehicle-brand:bentley",
      "urban-manufacturer:urban-automotive"
    ],
    "newTags": [
      "Car-Part",
      "Origin-GB",
      "Status-Active",
      "urban-family:exterior",
      "Arches",
      "Bentley",
      "Continental GT",
      "Urban Automotive",
      "store:urban",
      "urban-source:gp-portal",
      "urban-vehicle-brand:bentley",
      "urban-manufacturer:urban-automotive",
      "Bentley Continental GT Speed"
    ]
  },
  {
    "id": "cmmuk5evs001oe9v8z4uylurj",
    "sku": "URB-BUN-25358150-V1",
    "oldTags": [
      "Car-Part",
      "urban-family:bodykits",
      "Bentley",
      "Bundles",
      "Continental GT",
      "Urban Automotive",
      "store:urban",
      "urban-source:gp-portal",
      "urban-vehicle-brand:bentley",
      "urban-manufacturer:urban-automotive"
    ],
    "newTags": [
      "Car-Part",
      "urban-family:bodykits",
      "Bentley",
      "Bundles",
      "Continental GT",
      "Urban Automotive",
      "store:urban",
      "urban-source:gp-portal",
      "urban-vehicle-brand:bentley",
      "urban-manufacturer:urban-automotive",
      "Bentley Continental GT Speed"
    ]
  }
]