{
  "profile": "onecompany.global",
  "requestedAt": "2026-02-17T23:10:51.214Z",
  "importedCount": 12,
  "imported": [
    {
      "shortcode": "DU3A9YGDGJR",
      "action": "updated",
      "slug": "if-your-goal-is-minimal-unsprung-weight-and-maximum-du3a9ygdgjr",
      "date": "2026-02-17T16:36:40.000Z",
      "media": [
        "image"
      ]
    },
    {
      "shortcode": "DU0NUWGDNDV",
      "action": "updated",
      "slug": "looking-for-the-perfect-balance-between-style-handling-du0nuwgdndv",
      "date": "2026-02-16T14:30:29.000Z",
      "media": [
        "video"
      ]
    },
    {
      "shortcode": "DUUV-RJJALG",
      "action": "updated",
      "slug": "when-you-re-building-a-powerful-project-the-choice-duuv-rjjalg",
      "date": "2026-02-14T07:48:17.000Z",
      "media": [
        "video"
      ]
    },
    {
      "shortcode": "DUQANSJDP8U",
      "action": "updated",
      "slug": "this-cold-start-leaves-no-chance-to-go-unnoticed-duqansjdp8u",
      "date": "2026-02-12T15:25:07.000Z",
      "media": [
        "video"
      ]
    },
    {
      "shortcode": "DUN2XLEDKVQ",
      "action": "updated",
      "slug": "a-legendary-model-from-the-world-leader-in-forged-discs-dun2xledkvq",
      "date": "2026-02-11T15:28:35.000Z",
      "media": [
        "video"
      ]
    },
    {
      "shortcode": "DULQRIVDHIC",
      "action": "updated",
      "slug": "we-know-how-important-it-is-for-you-to-be-sure-of-the-dulqrivdhic",
      "date": "2026-02-10T15:16:41.000Z",
      "media": [
        "image",
        "image",
        "image",
        "image",
        "image"
      ]
    },
    {
      "shortcode": "DUIPNH6DBEK",
      "action": "updated",
      "slug": "want-to-add-even-more-aggression-and-personality-to-your-duipnh6dbek",
      "date": "2026-02-09T15:00:22.000Z",
      "media": [
        "image",
        "image",
        "image",
        "image",
        "image",
        "image"
      ]
    },
    {
      "shortcode": "DUBIS32DOTX",
      "action": "updated",
      "slug": "turn-your-bmw-g14-g15-g16-into-an-exclusive-project-dubis32dotx",
      "date": "2026-02-06T16:54:33.000Z",
      "media": [
        "image",
        "image",
        "image",
        "image",
        "image",
        "image",
        "image"
      ]
    },
    {
      "shortcode": "DUYUHJFDBSQ",
      "action": "added",
      "slug": "urban-automotive-is-a-modern-take-on-british-style-and-aggressiv-duyuhjfdbsq",
      "date": "2026-02-05T14:46:56.000Z",
      "media": [
        "video"
      ]
    },
    {
      "shortcode": "DUVVMLQDKCQ",
      "action": "added",
      "slug": "eventuri-for-the-new-bmw-m5-g90-duvvmlqdkcq",
      "date": "2026-02-04T14:43:12.000Z",
      "media": [
        "video"
      ]
    },
    {
      "shortcode": "DUTF_X9DPIL",
      "action": "added",
      "slug": "even-such-a-nuance-as-the-nozzles-of-the-exhaust-system-can-comp-dutf_x9dpil",
      "date": "2026-02-03T14:00:33.000Z",
      "media": [
        "image",
        "image",
        "image",
        "image",
        "image"
      ]
    },
    {
      "shortcode": "DTSKMDMJFGF",
      "action": "added",
      "slug": "one-company-dtskmdmjfgf",
      "date": "2026-01-19T11:10:24.000Z",
      "media": [
        "image"
      ]
    }
  ]
}